setup.py
lib/junos_netconify.egg-info/PKG-INFO
lib/junos_netconify.egg-info/SOURCES.txt
lib/junos_netconify.egg-info/dependency_links.txt
lib/junos_netconify.egg-info/requires.txt
lib/junos_netconify.egg-info/top_level.txt
lib/netconify/__init__.py
lib/netconify/cmdo.py
lib/netconify/constants.py
lib/netconify/facts.py
lib/netconify/tty.py
lib/netconify/tty_netconf.py
lib/netconify/tty_serial.py
lib/netconify/tty_telnet.py
tools/netconify