Metadata-Version: 1.1
Name: junos-netconify
Version: 1.0.2
Summary: Junos console/bootstrap automation
Home-page: http://www.github.com/Juniper/py-junos-netconify
Author: Jeremy Schulman
Author-email: jnpr-community-netdev@juniper.net
License: Apache 2.0
Keywords: Junos NETCONF basic CONSOLE automation
Platform: UNKNOWN
Classifier: Development Status :: 5 - Production/Stable
Classifier: Environment :: Console
Classifier: Intended Audience :: Developers
Classifier: Intended Audience :: Information Technology
Classifier: Intended Audience :: System Administrators
Classifier: Intended Audience :: Telecommunications Industry
Classifier: License :: OSI Approved :: Apache Software License
Classifier: Operating System :: OS Independent
Classifier: Programming Language :: Other Scripting Engines
Classifier: Programming Language :: Python
Classifier: Programming Language :: Python :: 2.6
Classifier: Programming Language :: Python :: 2.7
Classifier: Topic :: Software Development :: Libraries
Classifier: Topic :: Software Development :: Libraries :: Application Frameworks
Classifier: Topic :: Software Development :: Libraries :: Python Modules
Classifier: Topic :: System :: Networking
Classifier: Topic :: Text Processing :: Markup :: XML
